agenticraft/__init__.py
agenticraft/py.typed
agenticraft/agents/__init__.py
agenticraft/agents/reasoning.py
agenticraft/agents/workflow.py
agenticraft/cli/__init__.py
agenticraft/cli/main.py
agenticraft/cli/commands/__init__.py
agenticraft/cli/commands/new.py
agenticraft/cli/commands/plugin.py
agenticraft/cli/commands/run.py
agenticraft/cli/commands/templates.py
agenticraft/core/__init__.py
agenticraft/core/agent.py
agenticraft/core/config.py
agenticraft/core/exceptions.py
agenticraft/core/memory.py
agenticraft/core/plugin.py
agenticraft/core/provider.py
agenticraft/core/reasoning.py
agenticraft/core/telemetry.py
agenticraft/core/tool.py
agenticraft/core/types.py
agenticraft/core/workflow.py
agenticraft/memory/__init__.py
agenticraft/plugins/__init__.py
agenticraft/plugins/base.py
agenticraft/plugins/loader.py
agenticraft/plugins/registry.py
agenticraft/protocols/__init__.py
agenticraft/protocols/mcp/__init__.py
agenticraft/protocols/mcp/adapters.py
agenticraft/protocols/mcp/client.py
agenticraft/protocols/mcp/decorators.py
agenticraft/protocols/mcp/registry.py
agenticraft/protocols/mcp/server.py
agenticraft/protocols/mcp/types.py
agenticraft/providers/README.md
agenticraft/providers/__init__.py
agenticraft/providers/anthropic.py
agenticraft/providers/ollama.py
agenticraft/providers/openai.py
agenticraft/telemetry/__init__.py
agenticraft/telemetry/config.py
agenticraft/telemetry/decorators.py
agenticraft/telemetry/tracer.py
agenticraft/templates/__init__.py
agenticraft/tools/__init__.py
agenticraft/tools/calculator.py
agenticraft/tools/file_ops.py
agenticraft/tools/web.py
agenticraft/utils/__init__.py
agenticraft/utils/config.py
agenticraft/workflows/__init__.py
agenticraft-0.1.1.dist-info/licenses/LICENSE
agenticraft-0.1.1.dist-info/METADATA
agenticraft-0.1.1.dist-info/WHEEL
agenticraft-0.1.1.dist-info/entry_points.txt
agenticraft-0.1.1.dist-info/top_level.txt
agenticraft-0.1.1.dist-info/RECORD
