Metadata-Version: 2.4
Name: agenticraft
Version: 0.1.1
Summary: Dead simple AI agents with reasoning traces - build AI agents as simple as writing Python
Author-email: AgentiCraft Team <hello@agenticraft.ai>
License: Apache-2.0
Project-URL: Homepage, https://agenticraft.ai
Project-URL: Documentation, https://docs.agenticraft.ai
Project-URL: Repository, https://github.com/agenticraft/agenticraft
Project-URL: Issues, https://github.com/agenticraft/agenticraft/issues
Keywords: ai,agents,llm,openai,anthropic,claude,gpt,reasoning,mcp,model-context-protocol,observability,telemetry
Classifier: Development Status :: 3 - Alpha
Classifier: Intended Audience :: Developers
Classifier: License :: OSI Approved :: Apache Software License
Classifier: Programming Language :: Python :: 3
Classifier: Programming Language :: Python :: 3.10
Classifier: Programming Language :: Python :: 3.11
Classifier: Programming Language :: Python :: 3.12
Requires-Python: >=3.10
License-File: LICENSE
Requires-Dist: pydantic>=2.0
Requires-Dist: pydantic_settings>=2.0
Requires-Dist: httpx>=0.25.0
Requires-Dist: websockets>=12.0
Requires-Dist: typing-extensions>=4.9
Requires-Dist: python-dotenv>=1.0.0
Requires-Dist: opentelemetry-api>=1.20.0
Requires-Dist: opentelemetry-sdk>=1.20.0
Requires-Dist: pluggy>=1.3.0
Requires-Dist: structlog>=24.0
Provides-Extra: openai
Requires-Dist: openai>=1.0.0; extra == "openai"
Provides-Extra: anthropic
Requires-Dist: anthropic>=0.3.0; extra == "anthropic"
Provides-Extra: providers
Requires-Dist: openai>=1.0.0; extra == "providers"
Requires-Dist: anthropic>=0.3.0; extra == "providers"
Provides-Extra: telemetry
Requires-Dist: opentelemetry-exporter-otlp>=1.20.0; extra == "telemetry"
Requires-Dist: opentelemetry-exporter-jaeger>=1.20.0; extra == "telemetry"
Requires-Dist: opentelemetry-exporter-zipkin>=1.20.0; extra == "telemetry"
Requires-Dist: opentelemetry-instrumentation-httpx>=0.41b0; extra == "telemetry"
Requires-Dist: opentelemetry-instrumentation-grpc>=0.41b0; extra == "telemetry"
Provides-Extra: memory
Requires-Dist: chromadb>=0.4; extra == "memory"
Provides-Extra: api
Requires-Dist: fastapi>=0.100; extra == "api"
Requires-Dist: uvicorn>=0.23; extra == "api"
Provides-Extra: cli
Requires-Dist: rich>=13.0; extra == "cli"
Requires-Dist: click>=8.0; extra == "cli"
Provides-Extra: test
Requires-Dist: pytest>=7.4.0; extra == "test"
Requires-Dist: pytest-asyncio>=0.21.0; extra == "test"
Requires-Dist: pytest-cov>=4.1.0; extra == "test"
Requires-Dist: pytest-mock>=3.11.0; extra == "test"
Requires-Dist: pytest-timeout>=2.1.0; extra == "test"
Requires-Dist: pytest-xdist>=3.3.0; extra == "test"
Requires-Dist: coverage[toml]>=7.3.0; extra == "test"
Provides-Extra: dev
Requires-Dist: black>=23.7.0; extra == "dev"
Requires-Dist: ruff>=0.0.285; extra == "dev"
Requires-Dist: mypy>=1.5.0; extra == "dev"
Requires-Dist: pre-commit>=3.3.0; extra == "dev"
Provides-Extra: docs
Requires-Dist: mkdocs>=1.5.0; extra == "docs"
Requires-Dist: mkdocs-material>=9.0.0; extra == "docs"
Requires-Dist: mkdocstrings[python]>=0.24.0; extra == "docs"
Requires-Dist: mkdocs-gen-files>=0.5.0; extra == "docs"
Requires-Dist: mkdocs-literate-nav>=0.6.0; extra == "docs"
Requires-Dist: mkdocs-section-index>=0.3.0; extra == "docs"
Requires-Dist: mkdocs-autorefs>=0.5.0; extra == "docs"
Requires-Dist: pymdown-extensions>=10.0; extra == "docs"
Provides-Extra: all
Requires-Dist: agenticraft[api,cli,docs,memory,providers,telemetry]; extra == "all"
Dynamic: license-file
